quaac/__init__.py
quaac/attachments.py
quaac/common.py
quaac/models.py
quaac/version.py
quaac-1.0.1.dist-info/METADATA
quaac-1.0.1.dist-info/WHEEL
quaac-1.0.1.dist-info/RECORD
