Metadata-Version: 2.3
Name: quaac
Version: 1.0.1
Summary: A package for reading and writing QuAAC files.
Project-URL: Homepage, https://github.com/jrkerns/quaac
Project-URL: Issues, https://github.com/jrkerns/quaac/issues
Author-email: James Kerns <jkerns100@gmail.com>
License-Expression: MIT
Classifier: License :: OSI Approved :: MIT License
Classifier: Operating System :: OS Independent
Classifier: Programming Language :: Python :: 3
Requires-Python: >=3.8
Requires-Dist: email-validator
Requires-Dist: pydantic>=2.0.0
Requires-Dist: pyyaml
